LICENSE
README.md
setup.cfg
setup.py
dama/__init__.py
dama.egg-info/PKG-INFO
dama.egg-info/SOURCES.txt
dama.egg-info/dependency_links.txt
dama.egg-info/requires.txt
dama.egg-info/top_level.txt
dama/cm/__init__.py
dama/core/__init__.py
dama/core/axis.py
dama/core/binneddata.py
dama/core/edges.py
dama/core/grid.py
dama/core/gridarray.py
dama/core/griddata.py
dama/core/pointarray.py
dama/core/pointdata.py
dama/plotting/__init__.py
dama/plotting/stat_plot.py
dama/translations/__init__.py
dama/translations/histogram.py
dama/translations/interpolation.py
dama/translations/kde.py
dama/translations/lookup.py
dama/translations/ndimage.py
dama/translations/resample.py
dama/translations/translation.py
dama/utils/__init__.py
dama/utils/bind.py
dama/utils/fileio.py
dama/utils/formatter.py
dama/utils/stats.py