Metadata-Version: 2.1
Name: dama
Version: 0.4.7
Summary: Look at data in different ways
Home-page: https://github.com/philippeller/dama
Author: Philipp Eller
Author-email: peller.phys@gmail.com
License: Apache 2.0
Platform: UNKNOWN
Requires-Python: >=3.6
License-File: LICENSE
